gif_viewer/__init__.py
gif_viewer/frontend/build/index.html
gif_viewer/frontend/build/assets/index-C6LwRbhf.js
streamlit_gif_viewer_demo-0.1.0.dist-info/METADATA
streamlit_gif_viewer_demo-0.1.0.dist-info/WHEEL
streamlit_gif_viewer_demo-0.1.0.dist-info/top_level.txt
streamlit_gif_viewer_demo-0.1.0.dist-info/RECORD
